lando/__init__.py
lando/exceptions.py
lando/testutil.py
lando/client/__init__.py
lando/client/__main__.py
lando/common/__init__.py
lando/common/commands.py
lando/common/names.py
lando/k8s/__init__.py
lando/k8s/cluster.py
lando/k8s/config.py
lando/k8s/jobmanager.py
lando/k8s/lando.py
lando/k8s/watcher.py
lando/k8s/tests/__init__.py
lando/k8s/tests/test_cluster.py
lando/k8s/tests/test_config.py
lando/k8s/tests/test_jobmanager.py
lando/k8s/tests/test_lando.py
lando/k8s/tests/test_watcher.py
lando/server/__init__.py
lando/server/__main__.py
lando/server/cloudconfigscript.py
lando/server/cloudservice.py
lando/server/config.py
lando/server/jobapi.py
lando/server/lando.py
lando/server/tests/__init__.py
lando/server/tests/test_cloudconfigscript.py
lando/server/tests/test_cloudservice.py
lando/server/tests/test_config.py
lando/server/tests/test_jobapi.py
lando/server/tests/test_lando.py
lando/worker/__init__.py
lando/worker/__main__.py
lando/worker/config.py
lando/worker/worker.py
lando/worker/tests/__init__.py
lando/worker/tests/test_config.py
lando/worker/tests/test_worker.py
lando-0.11.3.dist-info/LICENSE
lando-0.11.3.dist-info/METADATA
lando-0.11.3.dist-info/WHEEL
lando-0.11.3.dist-info/entry_points.txt
lando-0.11.3.dist-info/top_level.txt
lando-0.11.3.dist-info/RECORD
