Metadata-Version: 2.1
Name: lando
Version: 0.11.3
Summary: Cloud based bioinformatics workflow runner
Home-page: https://github.com/Duke-GCB/lando
Author: Dan Leehr, John Bradley
Author-email: john.bradley@duke.edu
License: MIT
Platform: UNKNOWN
Requires-Dist: shade (==1.31.0)
Requires-Dist: DukeDSClient (==2.1.4)
Requires-Dist: humanfriendly (==2.4)
Requires-Dist: Jinja2 (==2.10.1)
Requires-Dist: kubernetes (==8.0.1)
Requires-Dist: pyasn1 (<0.5.0,>=0.4.1)
Requires-Dist: lando-messaging (==2.0.1)
Requires-Dist: Markdown (==2.6.9)
Requires-Dist: python-dateutil (==2.6.0)
Requires-Dist: PyYAML (==5.1)
Requires-Dist: requests (==2.20.1)
